__init__.py
Solutions/GridWorld/Action.py
Solutions/GridWorld/GridWorldEnvironment.py
Solutions/GridWorld/Policy.py
Solutions/GridWorld/State.py
Solutions/GridWorld/StateSpace.py
Solutions/GridWorld/__init__.py
Solutions/GridWorld/main.py
Tests/TestAction.py
Tests/TestState.py
Tests/TestStateSpace.py
Tests/__init__.py
src/Action.py
src/ActionProbabilityDistribution.py
src/State.py
src/StateActions.py
src/StateIndex.py
src/StateProbabilityDistribution.py
src/StateSpace.py
src/Agent/Agent.py
src/Agent/__init__.py
src/Environment/Environment.py
src/Environment/__init__.py
src/Policy/BasePolicy.py
src/Policy/EquiprobablePolicy.py
src/Policy/GreedyPolicy.py
umbrellarl-0.0.0.dist-info/METADATA
umbrellarl-0.0.0.dist-info/WHEEL
umbrellarl-0.0.0.dist-info/licenses/LICENSE
umbrellarl-0.0.0.dist-info/RECORD
