Metadata-Version: 2.1
Name: UmbrellaRL
Version: 0.0.0
Summary: Package to handle Reinforcement Learning functions. This package is nowhere near complete.
Project-URL: Homepage, https://github.com/ctorrington/UmbrellaRL
Project-URL: Issues, https://github.com/ctorrington/UmbrellaRL/issues
Author-email: Christopher Torrington <ctorrington1@gmail.com>
License-File: LICENSE
Classifier: License :: OSI Approved :: MIT License
Classifier: Operating System :: OS Independent
Classifier: Programming Language :: Python :: 3
Requires-Python: >=3.12
